scp_reader/__init__.py
scp_reader/__main__.py
scpreader-0.2.6.data/scripts/scp_reader
scpreader-0.2.6.dist-info/LICENSE
scpreader-0.2.6.dist-info/METADATA
scpreader-0.2.6.dist-info/WHEEL
scpreader-0.2.6.dist-info/top_level.txt
scpreader-0.2.6.dist-info/RECORD
